nonebot_plugin_imgexploration/__init__.py
nonebot_plugin_imgexploration/imgexploration.py
nonebot_plugin_imgexploration-0.4.4.dist-info/LICENSE.txt
nonebot_plugin_imgexploration-0.4.4.dist-info/METADATA
nonebot_plugin_imgexploration-0.4.4.dist-info/WHEEL
nonebot_plugin_imgexploration-0.4.4.dist-info/top_level.txt
nonebot_plugin_imgexploration-0.4.4.dist-info/RECORD
