Metadata-Version: 2.1
Name: nonebot-plugin-imgexploration
Version: 0.4.4
Summary: Nonebot2 插件，Google、Yandx和基于PicImageSearch的saucenao、ascii2d搜图
Home-page: https://github.com/cpuopt/nonebot_plugin_imgexploration
Author: cpufan
Author-email: cpufan2001@gmail.com
Keywords: nonebot nonebot-plugin imagesearch
Classifier: Development Status :: 3 - Alpha
Classifier: Intended Audience :: Developers
Classifier: Topic :: Software Development :: Build Tools
Classifier: License :: OSI Approved :: MIT License
Classifier: Programming Language :: Python :: 3.10
Classifier: Programming Language :: Python :: 3.11
Classifier: Programming Language :: Python
License-File: LICENSE.txt
Requires-Dist: colorama>=0.4.2
Requires-Dist: nonebot2>=2.0.0rc2
Requires-Dist: nonebot-adapter-onebot>=2.1.5
Requires-Dist: brotli>=1.0.0
Requires-Dist: PicImageSearch>=3.9.0
Requires-Dist: httpx>=0.23.0
Requires-Dist: lxml>=4.9.0
Requires-Dist: loguru>=0.6.0
Requires-Dist: pillow>=9.0.0
